LICENSE.txt
MANIFEST.in
README.rst
pyproject.toml
setup.py
tutor_xqueue.egg-info/PKG-INFO
tutor_xqueue.egg-info/SOURCES.txt
tutor_xqueue.egg-info/dependency_links.txt
tutor_xqueue.egg-info/entry_points.txt
tutor_xqueue.egg-info/requires.txt
tutor_xqueue.egg-info/top_level.txt
tutorxqueue/__about__.py
tutorxqueue/__init__.py
tutorxqueue/plugin.py
tutorxqueue/patches/caddyfile
tutorxqueue/patches/k8s-deployments
tutorxqueue/patches/k8s-jobs
tutorxqueue/patches/k8s-services
tutorxqueue/patches/kustomization-configmapgenerator
tutorxqueue/patches/local-docker-compose-dev-services
tutorxqueue/patches/local-docker-compose-jobs-services
tutorxqueue/patches/local-docker-compose-permissions-command
tutorxqueue/patches/local-docker-compose-permissions-volumes
tutorxqueue/patches/local-docker-compose-services
tutorxqueue/patches/openedx-common-settings
tutorxqueue/templates/xqueue/apps/settings/tutor.py
tutorxqueue/templates/xqueue/build/xqueue/Dockerfile
tutorxqueue/templates/xqueue/tasks/mysql/init
tutorxqueue/templates/xqueue/tasks/xqueue/init