Metadata-Version: 2.1
Name: tutor-xqueue
Version: 19.0.0
Summary: A Tutor plugin for Xqueue (external grading system)
Home-page: https://docs.tutor.edly.io/
Author: Edly
Author-email: hello@edly.io
Maintainer: eduNEXT
License: AGPLv3
Project-URL: Documentation, https://docs.tutor.edly.io/
Project-URL: Code, https://github.com/overhangio/tutor-xqueue
Project-URL: Issue tracker, https://github.com/overhangio/tutor-xqueue/issues
Project-URL: Community, https://discuss.openedx.org
Classifier: Development Status :: 5 - Production/Stable
Classifier: Intended Audience :: Developers
Classifier: License :: OSI Approved :: GNU Affero General Public License v3
Classifier: Operating System :: OS Independent
Classifier: Programming Language :: Python
Classifier: Programming Language :: Python :: 3.9
Classifier: Programming Language :: Python :: 3.10
Classifier: Programming Language :: Python :: 3.11
Classifier: Programming Language :: Python :: 3.12
Requires-Python: >=3.9
License-File: LICENSE.txt
Requires-Dist: tutor<20.0.0,>=19.0.0
Requires-Dist: requests
Provides-Extra: dev
Requires-Dist: tutor[dev]<20.0.0,>=19.0.0; extra == "dev"
